plain/tunnel/CHANGELOG.md
plain/tunnel/README.md
plain/tunnel/__init__.py
plain/tunnel/cli.py
plain/tunnel/client.py
plain/tunnel/entrypoints.py
plain_tunnel-0.8.2.dist-info/METADATA
plain_tunnel-0.8.2.dist-info/WHEEL
plain_tunnel-0.8.2.dist-info/entry_points.txt
plain_tunnel-0.8.2.dist-info/licenses/LICENSE
plain_tunnel-0.8.2.dist-info/RECORD
