Metadata-Version: 2.4
Name: plain.tunnel
Version: 0.8.2
Summary: Connect to your local development server remotely.
Author-email: Dave Gaeddert <dave.gaeddert@dropseed.dev>
License-Expression: BSD-3-Clause
License-File: LICENSE
Requires-Python: >=3.13
Requires-Dist: plain<1.0.0
Requires-Dist: websockets>=14.0
